concrete_db/__init__.py
concrete_db/crud.py
concrete_db/orm/__init__.py
concrete_db/orm/models.py
concrete_db/orm/setup.py
concrete_db-0.0.0.dist-info/METADATA
concrete_db-0.0.0.dist-info/WHEEL
concrete_db-0.0.0.dist-info/RECORD
