Metadata-Version: 2.3
Name: concrete-db
Version: 0.0.0
Summary: AI Agent Orchestration, Database Support
Requires-Python: <4.0.0,>=3.11.9
Requires-Dist: concrete-core
Requires-Dist: psycopg[binary]>=3.2.3
Requires-Dist: sqlmodel>=0.0.22
